Workbook
Name NativeTimeline_Order_Date: #N/A
Name Slicer_Category: #N/A
Name Slicer_Category1: #N/A
Name Slicer_Months__Order_Date: #N/A
Name Slicer_Product: #N/A

Sheet My Students
A1: Date | B1: First Name | C1: First Name | D1: Last Name | E1: Region | F1: Product | G1: Sales | H1: UPPER | I1: LOWER | J1: PROPER | K1: Full Name | L1: Region Sales
A2: 46023 | B2: AKSHAY SUNKARI | C2: =TRIM(B2) -> AKSHAY SUNKARI | D2: SUNKARI | E2: USA | F2: A | G2: 1200 | H2: =UPPER(C2) -> AKSHAY SUNKARI | I2: =LOWER(C2) -> akshay sunkari | J2: =PROPER(C2) -> Akshay Sunkari | K2: =_xlfn.CONCAT(C2," ",D2) -> AKSHAY SUNKARI SUNKARI | L2: =_xlfn.CONCAT(E2,"-",G2) -> USA-1200
A3: 46025 | B3: Anvesh Hirve | C3: =TRIM(B3) -> Anvesh Hirve | D3: Hirve | E3: Australia | F3: B | G3: 800 | H3: =UPPER(C3) -> ANVESH HIRVE | I3: =LOWER(C3) -> anvesh hirve | J3: =PROPER(C3) -> Anvesh Hirve | K3: =_xlfn.CONCAT(C3," ",D3) -> Anvesh Hirve Hirve | L3: =_xlfn.CONCAT(E3,"-",G3) -> Australia-800
A4: 46027 | B4: ATLURI CHARITHA SRI | C4: =TRIM(B4) -> ATLURI CHARITHA SRI | D4: CHARITHA SRI | E4: UK | F4: A | G4: 600 | H4: =UPPER(C4) -> ATLURI CHARITHA SRI | I4: =LOWER(C4) -> atluri charitha sri | J4: =PROPER(C4) -> Atluri Charitha Sri | K4: =_xlfn.CONCAT(C4," ",D4) -> ATLURI CHARITHA SRI CHARITHA SRI | L4: =_xlfn.CONCAT(E4,"-",G4) -> UK-600
A5: 46030 | B5: B Ramakrishna | C5: =TRIM(B5) -> B Ramakrishna | D5: Ramakrishna | E5: USA | F5: A | G5: 1500 | H5: =UPPER(C5) -> B RAMAKRISHNA | I5: =LOWER(C5) -> b ramakrishna | J5: =PROPER(C5) -> B Ramakrishna | K5: =_xlfn.CONCAT(C5," ",D5) -> B Ramakrishna Ramakrishna | L5: =_xlfn.CONCAT(E5,"-",G5) -> USA-1500
A6: 46034 | B6: Bhavana Koneti | C6: =TRIM(B6) -> Bhavana Koneti | D6: Koneti | E6: USA | F6: A | G6: 900 | H6: =UPPER(C6) -> BHAVANA KONETI | I6: =LOWER(C6) -> bhavana koneti | J6: =PROPER(C6) -> Bhavana Koneti | K6: =_xlfn.CONCAT(C6," ",D6) -> Bhavana Koneti Koneti | L6: =_xlfn.CONCAT(E6,"-",G6) -> USA-900
A7: 46037 | B7: Brijesh Mali | C7: =TRIM(B7) -> Brijesh Mali | D7: Mali | E7: Canada | F7: B | G7: 700 | H7: =UPPER(C7) -> BRIJESH MALI | I7: =LOWER(C7) -> brijesh mali | J7: =PROPER(C7) -> Brijesh Mali | K7: =_xlfn.CONCAT(C7," ",D7) -> Brijesh Mali Mali | L7: =_xlfn.CONCAT(E7,"-",G7) -> Canada-700
A8: 46042 | B8: Chandana Peddapelly | C8: =TRIM(B8) -> Chandana Peddapelly | D8: Peddapelly | E8: Australia | F8: C | G8: 1300 | H8: =UPPER(C8) -> CHANDANA PEDDAPELLY | I8: =LOWER(C8) -> chandana peddapelly | J8: =PROPER(C8) -> Chandana Peddapelly | K8: =_xlfn.CONCAT(C8," ",D8) -> Chandana Peddapelly Peddapelly | L8: =_xlfn.CONCAT(E8,"-",G8) -> Australia-1300
A9: 46047 | B9: Dinesh Kumar Bolla | C9: =TRIM(B9) -> Dinesh Kumar Bolla | D9: Bolla | E9: UK | F9: B | G9: 1100 | H9: =UPPER(C9) -> DINESH KUMAR BOLLA | I9: =LOWER(C9) -> dinesh kumar bolla | J9: =PROPER(C9) -> Dinesh Kumar Bolla | K9: =_xlfn.CONCAT(C9," ",D9) -> Dinesh Kumar Bolla Bolla | L9: =_xlfn.CONCAT(E9,"-",G9) -> UK-1100
A10: 46055 | B10: J Sujay | C10: =TRIM(B10) -> J Sujay | D10: Sujay | E10: USA | F10: A | G10: 750 | H10: =UPPER(C10) -> J SUJAY | I10: =LOWER(C10) -> j sujay | J10: =PROPER(C10) -> J Sujay | K10: =_xlfn.CONCAT(C10," ",D10) -> J Sujay Sujay | L10: =_xlfn.CONCAT(E10,"-",G10) -> USA-750
A11: 46058 | B11: Karrola Nagaraju | C11: =TRIM(B11) -> Karrola Nagaraju | D11: Nagaraju | E11: Canada | F11: C | G11: 1400 | H11: =UPPER(C11) -> KARROLA NAGARAJU | I11: =LOWER(C11) -> karrola nagaraju | J11: =PROPER(C11) -> Karrola Nagaraju | K11: =_xlfn.CONCAT(C11," ",D11) -> Karrola Nagaraju Nagaraju | L11: =_xlfn.CONCAT(E11,"-",G11) -> Canada-1400
A12: 46063 | B12: Lalam Satyanarayana | C12: =TRIM(B12) -> Lalam Satyanarayana | D12: Satyanarayana | E12: USA | F12: B | G12: 950 | H12: =UPPER(C12) -> LALAM SATYANARAYANA | I12: =LOWER(C12) -> lalam satyanarayana | J12: =PROPER(C12) -> Lalam Satyanarayana | K12: =_xlfn.CONCAT(C12," ",D12) -> Lalam Satyanarayana Satyanarayana | L12: =_xlfn.CONCAT(E12,"-",G12) -> USA-950
A13: 46067 | B13: Naveen Shivakoti | C13: =TRIM(B13) -> Naveen Shivakoti | D13: Shivakoti | E13: Australia | F13: A | G13: 680 | H13: =UPPER(C13) -> NAVEEN SHIVAKOTI | I13: =LOWER(C13) -> naveen shivakoti | J13: =PROPER(C13) -> Naveen Shivakoti | K13: =_xlfn.CONCAT(C13," ",D13) -> Naveen Shivakoti Shivakoti | L13: =_xlfn.CONCAT(E13,"-",G13) -> Australia-680
... A21: 46103 | B21: Thejaswini Padurthi | C21: =TRIM(B21) -> Thejaswini Padurthi | D21: Padurthi | E21: Canada | F21: B | G21: 980 | H21: =UPPER(C21) -> THEJASWINI PADURTHI | I21: =LOWER(C21) -> thejaswini padurthi | J21: =PROPER(C21) -> Thejaswini Padurthi | K21: =_xlfn.CONCAT(C21," ",D21) -> Thejaswini Padurthi Padurthi | L21: =_xlfn.CONCAT(E21,"-",G21) -> Canada-980

Sheet Sheet8
A1: Date | B1: First Name | C1: First Name | D1: Last Name | E1: Region | F1: Product | G1: Sales
A2: 46023 | B2: AKSHAY SUNKARI | C2: =TRIM(B2) -> AKSHAY SUNKARI | D2: SUNKARI | E2: USA | F2: A | G2: 1200
A3: 46025 | B3: Anvesh Hirve | C3: =TRIM(B3) -> Anvesh Hirve | D3: Hirve | E3: Australia | F3: B | G3: 800
A4: 46027 | B4: ATLURI CHARITHA SRI | C4: =TRIM(B4) -> ATLURI CHARITHA SRI | D4: CHARITHA SRI | E4: UK | F4: A | G4: 600
A5: 46030 | B5: B Ramakrishna | C5: =TRIM(B5) -> B Ramakrishna | D5: Ramakrishna | E5: USA | F5: A | G5: 1500
A6: 46034 | B6: Bhavana Koneti | C6: =TRIM(B6) -> Bhavana Koneti | D6: Koneti | E6: USA | F6: A | G6: 900
A7: 46037 | B7: Brijesh Mali | C7: =TRIM(B7) -> Brijesh Mali | D7: Mali | E7: Canada | F7: B | G7: 700
A8: 46042 | B8: Chandana Peddapelly | C8: =TRIM(B8) -> Chandana Peddapelly | D8: Peddapelly | E8: Australia | F8: C | G8: 1300
A9: 46047 | B9: Dinesh Kumar Bolla | C9: =TRIM(B9) -> Dinesh Kumar Bolla | D9: Bolla | E9: UK | F9: B | G9: 1100
A10: 46055 | B10: J Sujay | C10: =TRIM(B10) -> J Sujay | D10: Sujay | E10: USA | F10: A | G10: 750
A11: 46058 | B11: Karrola Nagaraju | C11: =TRIM(B11) -> Karrola Nagaraju | D11: Nagaraju | E11: Canada | F11: C | G11: 1400
A12: 46063 | B12: Lalam Satyanarayana | C12: =TRIM(B12) -> Lalam Satyanarayana | D12: Satyanarayana | E12: USA | F12: B | G12: 950
A13: 46067 | B13: Naveen Shivakoti | C13: =TRIM(B13) -> Naveen Shivakoti | D13: Shivakoti | E13: Australia | F13: A | G13: 680
... A21: 46103 | B21: Thejaswini Padurthi | C21: =TRIM(B21) -> Thejaswini Padurthi | D21: Padurthi | E21: Canada | F21: B | G21: 980

Sheet Sheet2
A1: Date | B1: Name | C1: First | D1: Name | E1: Region | F1: Product | G1: Sales | H1: Sales Category
A2: 46023 | B2: AKSHAY SUNKARI | C2: =TRIM(B2) -> AKSHAY SUNKARI | E2: USA | F2: A | G2: 1200 | H2: =IF(G2>800,"High Sales","Low Sales") -> High Sales
A3: 46025 | B3: Anvesh Hirve | C3: =TRIM(B3) -> Anvesh Hirve | E3: Australia | F3: B | G3: 800 | H3: =IF(G3>800,"High Sales","Low Sales") -> Low Sales | K3: 1 - How Many customers from USA - if we want to filter specific value inforamtion then we can use function called COUNTIF
A4: 46027 | B4: ATLURI CHARITHA SRI | C4: =TRIM(B4) -> ATLURI CHARITHA SRI | E4: UK | F4: A | G4: 600 | H4: =IF(G4>800,"High Sales","Low Sales") -> Low Sales | J4: COUNTIF & COUNT IFS
A5: 46030 | B5: B Ramakrishna | C5: =TRIM(B5) -> B Ramakrishna | E5: USA | F5: A | G5: 1500 | H5: =IF(G5>800,"High Sales","Low Sales") -> High Sales | J5: Date | K5: Name | L5: First | M5: Region | N5: Product | O5: Sales | Q5: How Many Sales Made in USA
A6: 46034 | B6: Bhavana Koneti | C6: =TRIM(B6) -> Bhavana Koneti | E6: USA | F6: A | G6: 900 | H6: =IF(G6>800,"High Sales","Low Sales") -> High Sales | J6: 46023 | K6: AKSHAY SUNKARI | L6: =TRIM(K6) -> AKSHAY SUNKARI | M6: USA | N6: A | O6: 1200 | Q6: =COUNTIF(M6:M25,"USA") -> 6
A7: 46037 | B7: Brijesh Mali | C7: =TRIM(B7) -> Brijesh Mali | E7: Canada | F7: B | G7: 700 | H7: =IF(G7>800,"High Sales","Low Sales") -> Low Sales | J7: 46025 | K7: Anvesh Hirve | L7: =TRIM(K7) -> Anvesh Hirve | M7: Australia | N7: B | O7: 800
A8: 46042 | B8: Chandana Peddapelly | C8: =TRIM(B8) -> Chandana Peddapelly | E8: Australia | F8: C | G8: 1300 | H8: =IF(G8>800,"High Sales","Low Sales") -> High Sales | J8: 46027 | K8: ATLURI CHARITHA SRI | L8: =TRIM(K8) -> ATLURI CHARITHA SRI | M8: UK | N8: A | O8: 600 | Q8: How Many Sales for Product A in USA
A9: 46047 | B9: Dinesh Kumar Bolla | C9: =TRIM(B9) -> Dinesh Kumar Bolla | E9: UK | F9: B | G9: 1100 | H9: =IF(G9>800,"High Sales","Low Sales") -> High Sales | J9: 46030 | K9: B Ramakrishna | L9: =TRIM(K9) -> B Ramakrishna | M9: USA | N9: A | O9: 1500 | Q9: =COUNTIFS(M6:M25,"USA",N6:N25,"A") -> 3
A10: 46055 | B10: J Sujay | C10: =TRIM(B10) -> J Sujay | E10: USA | F10: A | G10: 750 | H10: =IF(G10>800,"High Sales","Low Sales") -> Low Sales | J10: 46034 | K10: Bhavana Koneti | L10: =TRIM(K10) -> Bhavana Koneti | M10: USA | N10: B | O10: 900
A11: 46058 | B11: Karrola Nagaraju | C11: =TRIM(B11) -> Karrola Nagaraju | E11: Canada | F11: C | G11: 1400 | H11: =IF(G11>800,"High Sales","Low Sales") -> High Sales | J11: 46037 | K11: Brijesh Mali | L11: =TRIM(K11) -> Brijesh Mali | M11: Canada | N11: B | O11: 700
A12: 46063 | B12: Lalam Satyanarayana | C12: =TRIM(B12) -> Lalam Satyanarayana | E12: USA | F12: B | G12: 950 | H12: =IF(G12>800,"High Sales","Low Sales") -> High Sales | J12: 46042 | K12: Chandana Peddapelly | L12: =TRIM(K12) -> Chandana Peddapelly | M12: Australia | N12: C | O12: 1300 | Q12: What is the total sales in USA
A13: 46067 | B13: Naveen Shivakoti | C13: =TRIM(B13) -> Naveen Shivakoti | E13: Australia | F13: A | G13: 680 | H13: =IF(G13>800,"High Sales","Low Sales") -> Low Sales | J13: 46047 | K13: Dinesh Kumar Bolla | L13: =TRIM(K13) -> Dinesh Kumar Bolla | M13: UK | N13: B | O13: 1100 | Q13: SUMIF
A14: 46071 | B14: rudra premkumar | C14: =TRIM(B14) -> rudra premkumar | E14: UK | F14: C | G14: 1600 | H14: =IF(G14>800,"High Sales","Low Sales") -> High Sales | J14: 46055 | K14: J Sujay | L14: =TRIM(K14) -> J Sujay | M14: USA | N14: A | O14: 750 | Q14: =SUMIF(M6:M25,"USA",O6:O25) -> 7000
A15: 46075 | B15: Samiksha Moharana | C15: =TRIM(B15) -> Samiksha Moharana | E15: Germany | F15: B | G15: 1000 | H15: =IF(G15>800,"High Sales","Low Sales") -> High Sales | J15: 46058 | K15: Karrola Nagaraju | L15: =TRIM(K15) -> Karrola Nagaraju | M15: Canada | N15: C | O15: 1400 | Q15: What is the total sales for Product A in USA
A16: 46080 | B16: Shivaprathap Singiri | C16: =TRIM(B16) -> Shivaprathap Singiri | E16: Canada | F16: B | G16: 720 | H16: =IF(G16>800,"High Sales","Low Sales") -> Low Sales | J16: 46063 | K16: Lalam Satyanarayana | L16: =TRIM(K16) -> Lalam Satyanarayana | M16: USA | N16: B | O16: 950 | Q16: SUMIFS
A17: 46084 | B17: Shriya Mechineni | C17: =TRIM(B17) -> Shriya Mechineni | E17: USA | F17: C | G17: 1700 | H17: =IF(G17>800,"High Sales","Low Sales") -> High Sales | J17: 46067 | K17: Naveen Shivakoti | L17: =TRIM(K17) -> Naveen Shivakoti | M17: Australia | N17: A | O17: 680 | Q17: =SUMIFS(O6:O25,M6:M25,"USA",N6:N25,"A") -> 3450
A18: 46088 | B18: Siri Mandadapu | C18: =TRIM(B18) -> Siri Mandadapu | E18: Australia | F18: B | G18: 1050 | H18: =IF(G18>800,"High Sales","Low Sales") -> High Sales | J18: 46071 | K18: rudra premkumar | L18: =TRIM(K18) -> rudra premkumar | M18: UK | N18: C | O18: 1600
A19: 46093 | B19: SLVSNTejaswi-kota | C19: =TRIM(B19) -> SLVSNTejaswi-kota | E19: UK | F19: A | G19: 800 | H19: =IF(G19>800,"High Sales","Low Sales") -> Low Sales | J19: 46075 | K19: Samiksha Moharana | L19: =TRIM(K19) -> Samiksha Moharana | M19: Germany | N19: B | O19: 1000 | Q19: Average sales for USA
A20: 46099 | B20: suma sri priya | C20: =TRIM(B20) -> suma sri priya | E20: Germany | F20: C | G20: 1550 | H20: =IF(G20>800,"High Sales","Low Sales") -> High Sales | J20: 46080 | K20: Shivaprathap Singiri | L20: =TRIM(K20) -> Shivaprathap Singiri | M20: Canada | N20: B | O20: 720 | Q20: Average sales for Product B in USA
A21: 46103 | B21: Thejaswini Padurthi | C21: =TRIM(B21) -> Thejaswini Padurthi | E21: Canada | F21: B | G21: 980 | H21: =IF(G21>800,"High Sales","Low Sales") -> High Sales | J21: 46084 | K21: Shriya Mechineni | L21: =TRIM(K21) -> Shriya Mechineni | M21: USA | N21: C | O21: 1700
J22: 46088 | K22: Siri Mandadapu | L22: =TRIM(K22) -> Siri Mandadapu | M22: Australia | N22: B | O22: 1050
J23: 46093 | K23: SLVSNTejaswi-kota | L23: =TRIM(K23) -> SLVSNTejaswi-kota | M23: UK | N23: A | O23: 800
J24: 46099 | K24: suma sri priya | L24: =TRIM(K24) -> suma sri priya | M24: Germany | N24: C | O24: 1550
J25: 46103 | K25: Thejaswini Padurthi | L25: =TRIM(K25) -> Thejaswini Padurthi | M25: Canada | N25: B | O25: 980

Sheet Order details
A1: VLOOKUP | K1: XLOOKUP
A2: Order ID | B2: CustomerID | C2: Product Name | D2: Quantity | E2: City | F2: Customer Name | I2: Order ID | J2: CustomerID | K2: Product Name | L2: Quantity | M2: CustomerName | N2: City
A3: ORD1001 | B3: C001 | C3: Laptop | D3: 2 | E3: =VLOOKUP(B3,'Customer details'!A2:C10,2,FALSE) -> New York | F3: =VLOOKUP('Order details'!B3,'Customer details'!A2:C10,3,FALSE) -> akshay sunkari | I3: ORD1001 | J3: C001 | K3: Laptop | L3: 2 | M3: =_xlfn.XLOOKUP(J3,'Customer details'!A2:A10,'Customer details'!C2:C10,) -> akshay sunkari | N3: =_xlfn.XLOOKUP(J3,'Customer details'!A2:A10,'Customer details'!B2:B10) -> New York
A4: ORD1002 | B4: C003 | C4: Mouse | D4: 5 | E4: =VLOOKUP(B4,'Customer details'!A3:C11,2,FALSE) -> Paris | F4: =VLOOKUP('Order details'!B4,'Customer details'!A3:C11,3,FALSE) -> atluri charitha sri | I4: ORD1002 | J4: C003 | K4: Mouse | L4: 5 | M4: =_xlfn.XLOOKUP(J4,'Customer details'!A3:A11,'Customer details'!C3:C11,) -> atluri charitha sri | N4: =_xlfn.XLOOKUP(J4,'Customer details'!A3:A11,'Customer details'!B3:B11) -> Paris
A5: ORD1003 | B5: C004 | C5: Keyboard | D5: 3 | E5: =VLOOKUP(B5,'Customer details'!A4:C12,2,FALSE) -> Cairo | F5: =VLOOKUP('Order details'!B5,'Customer details'!A4:C12,3,FALSE) -> b ramakrishna | I5: ORD1003 | J5: C004 | K5: Keyboard | L5: 3 | M5: =_xlfn.XLOOKUP(J5,'Customer details'!A4:A12,'Customer details'!C4:C12,) -> b ramakrishna | N5: =_xlfn.XLOOKUP(J5,'Customer details'!A4:A12,'Customer details'!B4:B12) -> Cairo
A6: ORD1005 | B6: C007 | C6: Printer | D6: 2 | E6: =VLOOKUP(B6,'Customer details'!A5:C13,2,FALSE) -> London | F6: =VLOOKUP('Order details'!B6,'Customer details'!A5:C13,3,FALSE) -> chandana peddapelly | I6: ORD1005 | J6: C007 | K6: Printer | L6: 2 | M6: =_xlfn.XLOOKUP(J6,'Customer details'!A5:A13,'Customer details'!C5:C13,) -> chandana peddapelly | N6: =_xlfn.XLOOKUP(J6,'Customer details'!A5:A13,'Customer details'!B5:B13) -> London
A7: ORD1006 | B7: C006 | C7: Laptop | D7: 2 | E7: =VLOOKUP(B7,'Customer details'!A6:C14,2,FALSE) -> New York | F7: =VLOOKUP('Order details'!B7,'Customer details'!A6:C14,3,FALSE) -> brijesh mali | I7: ORD1006 | J7: C006 | K7: Laptop | L7: 2 | M7: =_xlfn.XLOOKUP(J7,'Customer details'!A6:A14,'Customer details'!C6:C14,) -> brijesh mali | N7: =_xlfn.XLOOKUP(J7,'Customer details'!A6:A14,'Customer details'!B6:B14) -> New York
A8: ORD1008 | B8: C008 | C8: Keyboard | D8: 3 | E8: =VLOOKUP(B8,'Customer details'!A7:C15,2,FALSE) -> Paris | F8: =VLOOKUP('Order details'!B8,'Customer details'!A7:C15,3,FALSE) -> dinesh kumar bolla | I8: ORD1008 | J8: C008 | K8: Keyboard | L8: 3 | M8: =_xlfn.XLOOKUP(J8,'Customer details'!A7:A15,'Customer details'!C7:C15,) -> dinesh kumar bolla | N8: =_xlfn.XLOOKUP(J8,'Customer details'!A7:A15,'Customer details'!B7:B15) -> Paris
A9: ORD1009 | B9: C009 | C9: Monitor | D9: 1 | E9: =VLOOKUP(B9,'Customer details'!A8:C16,2,FALSE) -> Cairo | F9: =VLOOKUP('Order details'!B9,'Customer details'!A8:C16,3,FALSE) -> j sujay | I9: ORD1009 | J9: C009 | K9: Monitor | L9: 1 | M9: =_xlfn.XLOOKUP(J9,'Customer details'!A8:A16,'Customer details'!C8:C16,) -> j sujay | N9: =_xlfn.XLOOKUP(J9,'Customer details'!A8:A16,'Customer details'!B8:B16) -> Cairo
A12: HLOOKUP
A13: Customer ID | B13: C001 | C13: C002 | D13: C003 | E13: C004 | F13: C005 | I13: CustomerID | J13: City | M13: Absolute Reference
A14: Name | B14: akshay sunkari | C14: anvesh hirve | D14: atluri charitha sri | E14: b ramakrishna | F14: bhavana koneti | I14: C001 | J14: =HLOOKUP(I14,$B$13:$F$15,3,FALSE) -> New York | K14: =HLOOKUP(I14,$B$13:$F$15,2,FALSE) -> akshay sunkari
A15: City | B15: New York | C15: London | D15: Paris | E15: Cairo | F15: Rome | I15: C002 | J15: =HLOOKUP(I15,$B$13:$F$15,3,FALSE) -> London | K15: =HLOOKUP(I15,$B$13:$F$15,2,FALSE) -> anvesh hirve
I16: C003 | J16: =HLOOKUP(I16,$B$13:$F$15,3,FALSE) -> Paris | K16: =HLOOKUP(I16,$B$13:$F$15,2,FALSE) -> atluri charitha sri
I17: C004 | J17: =HLOOKUP(I17,$B$13:$F$15,3,FALSE) -> Cairo | K17: =HLOOKUP(I17,$B$13:$F$15,2,FALSE) -> b ramakrishna
I18: C005 | J18: =HLOOKUP(I18,$B$13:$F$15,3,FALSE) -> Rome | K18: =HLOOKUP(I18,$B$13:$F$15,2,FALSE) -> bhavana koneti
I20: C004 | J20: =HLOOKUP(I20,$B$13:$F$15,3,FALSE) -> Cairo

Sheet Data validation 
A1: Employee Name | B1: DepartMent Name | E1: Salary | F1: New Departmnet Name | L1: Department Name | N1: Column1
A2: AKSHAY SUNKARI | B2: HR | C2: IT | D2: HR | E2: 21000 | L2: SC | N2: DepartmentName
A3: Anvesh Hirve | B3: IT | C3: HR | D3: SC | E3: 50000 | L3: IT | N3: SC
A4: ATLURI CHARITHA SRI | B4: HR | C4: FI | L4: HR | N4: IT
A5: B Ramakrishna | B5: Finance | C5: HR | G5: it should allow departments Name as HR, IT, Finanace | L5: Finanace | N5: HR
A6: Bhavana Koneti | B6: IT | C6: IT | L6: Facility
A7: Brijesh Mali | B7: HR | C7: Finance | I7: HR - Human resources

Sheet Customer details
A1: CustomerID | B1: City | C1: Customer Name
A2: C001 | B2: New York | C2: akshay sunkari
A3: C002 | B3: London | C3: anvesh hirve
A4: C003 | B4: Paris | C4: atluri charitha sri
A5: C004 | B5: Cairo | C5: b ramakrishna
A6: C005 | B6: Rome | C6: bhavana koneti
A7: C006 | B7: New York | C7: brijesh mali
A8: C007 | B8: London | C8: chandana peddapelly
A9: C008 | B9: Paris | C9: dinesh kumar bolla
A10: C009 | B10: Cairo | C10: j sujay

Sheet Sheet4
A1: Customer ID | B1: C001 | C1: C002 | D1: C003 | E1: C004 | F1: C005
A2: Name | B2: akshay sunkari | C2: anvesh hirve | D2: atluri charitha sri | E2: b ramakrishna | F2: bhavana koneti
A3: City | B3: New York | C3: London | D3: Paris | E3: Cairo | F3: Rome

Sheet Sheet5
A1: Order Date | B1: Region | C1: Salesperson | D1: Product | E1: Category | F1: Quantity | G1: Unit Price | H1: Sales | I1: Month Name | J1: Column1 | K1: Column2
A2: 45700 | B2: North | C2: Michael | D2: Keyboard | E2: Accessories | F2: 7 | G2: 45 | H2: 315 | I2: =TEXT(Table1[[#This Row],[Order Date]],"MMMM") -> February | J2: =MONTH(Table1[[#This Row],[Order Date]]) -> 2 | K2: =TEXT(Table1[[#This Row],[Order Date]],"MMM") -> Feb
A3: 45727 | B3: North | C3: David | D3: Monitor | E3: Electronics | F3: 6 | G3: 350 | H3: 2100 | I3: =TEXT(Table1[[#This Row],[Order Date]],"MMMM") -> March | J3: =MONTH(Table1[[#This Row],[Order Date]]) -> 3 | K3: =TEXT(Table1[[#This Row],[Order Date]],"MMM") -> Mar
A4: 45663 | B4: West | C4: Michael | D4: Monitor | E4: Electronics | F4: 7 | G4: 350 | H4: 2450 | I4: =TEXT(Table1[[#This Row],[Order Date]],"MMMM") -> January | J4: =MONTH(Table1[[#This Row],[Order Date]]) -> 1 | K4: =TEXT(Table1[[#This Row],[Order Date]],"MMM") -> Jan
A5: 45689 | B5: North | C5: Michael | D5: Monitor | E5: Electronics | F5: 7 | G5: 350 | H5: 2450 | I5: =TEXT(Table1[[#This Row],[Order Date]],"MMMM") -> February | J5: =MONTH(Table1[[#This Row],[Order Date]]) -> 2 | K5: =TEXT(Table1[[#This Row],[Order Date]],"MMM") -> Feb
A6: 45687 | B6: North | C6: David | D6: Laptop | E6: Electronics | F6: 7 | G6: 900 | H6: 6300 | I6: =TEXT(Table1[[#This Row],[Order Date]],"MMMM") -> January | J6: =MONTH(Table1[[#This Row],[Order Date]]) -> 1 | K6: =TEXT(Table1[[#This Row],[Order Date]],"MMM") -> Jan
A7: 45664 | B7: West | C7: Emma | D7: Keyboard | E7: Accessories | F7: 5 | G7: 45 | H7: 225 | I7: =TEXT(Table1[[#This Row],[Order Date]],"MMMM") -> January | J7: =MONTH(Table1[[#This Row],[Order Date]]) -> 1 | K7: =TEXT(Table1[[#This Row],[Order Date]],"MMM") -> Jan
A8: 45728 | B8: South | C8: Michael | D8: Monitor | E8: Electronics | F8: 5 | G8: 350 | H8: 1750 | I8: =TEXT(Table1[[#This Row],[Order Date]],"MMMM") -> March | J8: =MONTH(Table1[[#This Row],[Order Date]]) -> 3 | K8: =TEXT(Table1[[#This Row],[Order Date]],"MMM") -> Mar
A9: 45733 | B9: North | C9: Michael | D9: Mouse | E9: Accessories | F9: 6 | G9: 25 | H9: 150 | I9: =TEXT(Table1[[#This Row],[Order Date]],"MMMM") -> March | J9: =MONTH(Table1[[#This Row],[Order Date]]) -> 3 | K9: =TEXT(Table1[[#This Row],[Order Date]],"MMM") -> Mar
A10: 45731 | B10: West | C10: Benjamin | D10: Laptop | E10: Electronics | F10: 4 | G10: 900 | H10: 3600 | I10: =TEXT(Table1[[#This Row],[Order Date]],"MMMM") -> March | J10: =MONTH(Table1[[#This Row],[Order Date]]) -> 3 | K10: =TEXT(Table1[[#This Row],[Order Date]],"MMM") -> Mar
A11: 45699 | B11: East | C11: Olivia | D11: Headset | E11: Accessories | F11: 8 | G11: 80 | H11: 640 | I11: =TEXT(Table1[[#This Row],[Order Date]],"MMMM") -> February | J11: =MONTH(Table1[[#This Row],[Order Date]]) -> 2 | K11: =TEXT(Table1[[#This Row],[Order Date]],"MMM") -> Feb
A12: 45690 | B12: North | C12: Olivia | D12: Keyboard | E12: Accessories | F12: 4 | G12: 45 | H12: 180 | I12: =TEXT(Table1[[#This Row],[Order Date]],"MMMM") -> February | J12: =MONTH(Table1[[#This Row],[Order Date]]) -> 2 | K12: =TEXT(Table1[[#This Row],[Order Date]],"MMM") -> Feb
A13: 45726 | B13: West | C13: Olivia | D13: Headset | E13: Accessories | F13: 6 | G13: 80 | H13: 480 | I13: =TEXT(Table1[[#This Row],[Order Date]],"MMMM") -> March | J13: =MONTH(Table1[[#This Row],[Order Date]]) -> 3 | K13: =TEXT(Table1[[#This Row],[Order Date]],"MMM") -> Mar
... A102: 45749 | B102: South | C102: Marta | D102: Keyboard | E102: Accessories | F102: 1 | G102: 100 | H102: 100 | I102: =TEXT(Table1[[#This Row],[Order Date]],"MMMM") -> April | J102: =MONTH(Table1[[#This Row],[Order Date]]) -> 4 | K102: =TEXT(Table1[[#This Row],[Order Date]],"MMM") -> Apr

Sheet Sheet11
A2: Category | B2: Accessories
A4: Order date | B4: Sum of Sales
A5: West | B5: 225
A6: Grand Total | B6: 225

Sheet Pivot Tables
A3: Row Labels | B3: Sum of Sales | D3: Row Labels | E3: Sum of Sales | G3: Row Labels | H3: Sum of Sales | J3: Row Labels | K3: Average of Sales
A4: East | B4: 2735 | D4: Accessories | E4: 10985 | G4: Jan | H4: 51510 | J4: East | K4: 1897.2222
A5: North | B5: 3645 | D5: Electronics | E5: 71350 | G5: Feb | H5: 28615 | J5: North | K5: 760
A6: South | B6: 1375 | D6: Furniture | E6: 25680 | G6: Mar | H6: 34345 | J6: South | K6: 473.33333
A7: West | B7: 3230 | D7: Office | E7: 6600 | G7: Apr | H7: 145 | J7: West | K7: 960
A8: Grand Total | B8: 10985 | D8: Grand Total | E8: 114615 | G8: Grand Total | H8: 114615 | J8: Grand Total | K8: 1192.2917

Sheet Charts
A1: Column Chart & Pie and Dounut chart | D1: Barchart | G1: Line Chart/Area chart | J1: Scatter chart | M1: Combochart
A2: Region | B2: Total Sales | D2: Product | E2: Sales | G2: Month | H2: Sales | J2: Advertising | K2: Sales | M2: Month | N2: Revenue | O2: Profit
A3: North | B3: 18450 | D3: Laptop | E3: 12000 | G3: Jan | H3: 4200 | J3: 1000 | K3: 5200 | M3: Jan | N3: 12000 | O3: 2200
A4: South | B4: 14200 | D4: Monitor | E4: 8200 | G4: Feb | H4: 5100 | J4: 1500 | K4: 6800 | M4: Feb | N4: 15000 | O4: 3100
A5: East | B5: 16900 | D5: Printer | E5: 5100 | G5: Mar | H5: 4800 | J5: 2000 | K5: 8100 | M5: Mar | N5: 17000 | O5: 3600
A6: West | B6: 12750 | D6: Keyboard | E6: 3400 | G6: Apr | H6: 6300 | J6: 2500 | K6: 9300 | M6: Apr | N6: 18000 | O6: 4100
D7: Mouse | E7: 2600 | G7: May | H7: 7000 | J7: 3000 | K7: 11100 | M7: May | N7: 22000 | O7: 5200
G8: Jun | H8: 7600 | J8: 3500 | K8: 12300 | M8: Jun | N8: 25000 | O8: 6100
G9: Jul | H9: 8100
G10: Aug | H10: 8500
G11: Sep | H11: 7900
G12: Oct | H12: 8800
G13: Nov | H13: 9300
G14: Dec | H14: 10100

Sheet Dashboard

Sheet Sales Data
A1: Order Date | B1: Region | C1: Sales Person Name | D1: Product | E1: Category | F1: Quantity | G1: Unit Price | H1: Sales | I1: MonthName
A2: 45700 | B2: North | C2: AKSHAY SUNKARI | D2: Keyboard | E2: Accessories | F2: 7 | G2: 45 | H2: 315 | I2: =TEXT(Table5[[#This Row],[Order Date]],"MMM") -> Feb
A3: 45727 | B3: North | C3: Anvesh Hirve | D3: Monitor | E3: Electronics | F3: 6 | G3: 350 | H3: 2100 | I3: =TEXT(Table5[[#This Row],[Order Date]],"MMM") -> Mar
A4: 45663 | B4: West | C4: ATLURI CHARITHA SRI | D4: Monitor | E4: Electronics | F4: 7 | G4: 350 | H4: 2450 | I4: =TEXT(Table5[[#This Row],[Order Date]],"MMM") -> Jan
A5: 45689 | B5: North | C5: B Ramakrishna | D5: Monitor | E5: Electronics | F5: 7 | G5: 350 | H5: 2450 | I5: =TEXT(Table5[[#This Row],[Order Date]],"MMM") -> Feb
A6: 45687 | B6: North | C6: Bhavana Koneti | D6: Laptop | E6: Electronics | F6: 7 | G6: 900 | H6: 6300 | I6: =TEXT(Table5[[#This Row],[Order Date]],"MMM") -> Jan
A7: 45664 | B7: West | C7: Brijesh Mali | D7: Keyboard | E7: Accessories | F7: 5 | G7: 45 | H7: 225 | I7: =TEXT(Table5[[#This Row],[Order Date]],"MMM") -> Jan
A8: 45728 | B8: South | C8: Chandana Peddapelly | D8: Monitor | E8: Electronics | F8: 5 | G8: 350 | H8: 1750 | I8: =TEXT(Table5[[#This Row],[Order Date]],"MMM") -> Mar
A9: 45733 | B9: North | C9: Dinesh Kumar Bolla | D9: Mouse | E9: Accessories | F9: 6 | G9: 25 | H9: 150 | I9: =TEXT(Table5[[#This Row],[Order Date]],"MMM") -> Mar
A10: 45731 | B10: West | C10: J Sujay | D10: Laptop | E10: Electronics | F10: 4 | G10: 900 | H10: 3600 | I10: =TEXT(Table5[[#This Row],[Order Date]],"MMM") -> Mar
A11: 45699 | B11: East | C11: Karrola Nagaraju | D11: Headset | E11: Accessories | F11: 8 | G11: 80 | H11: 640 | I11: =TEXT(Table5[[#This Row],[Order Date]],"MMM") -> Feb
A12: 45690 | B12: North | C12: Lalam Satyanarayana | D12: Keyboard | E12: Accessories | F12: 4 | G12: 45 | H12: 180 | I12: =TEXT(Table5[[#This Row],[Order Date]],"MMM") -> Feb
A13: 45726 | B13: West | C13: Naveen Shivakoti | D13: Headset | E13: Accessories | F13: 6 | G13: 80 | H13: 480 | I13: =TEXT(Table5[[#This Row],[Order Date]],"MMM") -> Mar
... A102: 45749 | B102: South | C102: Thejaswini Padurthi | D102: Keyboard | E102: Accessories | F102: 1 | G102: 100 | H102: 100 | I102: =TEXT(Table5[[#This Row],[Order Date]],"MMM") -> Apr

Sheet Charts Data
A1: Column Chart & Pie and Dounut chart | D1: Barchart | G1: Line Chart/Area chart | J1: Scatter chart | M1: Combochart
A2: Region | B2: Total Sales | D2: Product | E2: Sales | G2: Month | H2: Sales | J2: Advertising | K2: Sales | M2: Month | N2: Revenue | O2: Profit
A3: North | B3: 18450 | D3: Laptop | E3: 12000 | G3: Jan | H3: 4200 | J3: 1000 | K3: 5200 | M3: Jan | N3: 12000 | O3: 2200
A4: South | B4: 14200 | D4: Monitor | E4: 8200 | G4: Feb | H4: 5100 | J4: 1500 | K4: 6800 | M4: Feb | N4: 15000 | O4: 3100
A5: East | B5: 16900 | D5: Printer | E5: 5100 | G5: Mar | H5: 4800 | J5: 2000 | K5: 8100 | M5: Mar | N5: 17000 | O5: 3600
A6: West | B6: 12750 | D6: Keyboard | E6: 3400 | G6: Apr | H6: 6300 | J6: 2500 | K6: 9300 | M6: Apr | N6: 18000 | O6: 4100
D7: Mouse | E7: 2600 | G7: May | H7: 7000 | J7: 3000 | K7: 11100 | M7: May | N7: 22000 | O7: 5200
G8: Jun | H8: 7600 | J8: 3500 | K8: 12300 | M8: Jun | N8: 25000 | O8: 6100
G9: Jul | H9: 8100
G10: Aug | H10: 8500
G11: Sep | H11: 7900
G12: Oct | H12: 8800
G13: Nov | H13: 9300
G14: Dec | H14: 10100
